README.md
setup.py
django_url_renditions.egg-info/PKG-INFO
django_url_renditions.egg-info/SOURCES.txt
django_url_renditions.egg-info/dependency_links.txt
django_url_renditions.egg-info/requires.txt
django_url_renditions.egg-info/top_level.txt
url_renditions/__init__.py
url_renditions/apps.py
url_renditions/fields.py
url_renditions/graphql_schema.py
url_renditions/models.py
url_renditions/render.py
url_renditions/render_mp3.py
url_renditions/resize_image.py
url_renditions/tests.py
url_renditions/views.py
url_renditions/management/__init__.py
url_renditions/management/commands/__init__.py
url_renditions/management/commands/renditions.py
url_renditions/migrations/0001_initial.py
url_renditions/migrations/0002_auto_20210615_1737.py
url_renditions/migrations/__init__.py