Metadata-Version: 2.1
Name: django-url-renditions
Version: 1.4
Summary: Create custom renditions from django url fields
Home-page: https://github.com/vied12/django-url-renditions
Author: Edouard Richard
Author-email: edou4rd@gmail.com
License: BSD License
Platform: UNKNOWN
Classifier: Environment :: Web Environment
Classifier: Framework :: Django
Classifier: Framework :: Django :: 1.11
Classifier: Intended Audience :: Developers
Classifier: License :: OSI Approved :: BSD License
Classifier: Operating System :: OS Independent
Classifier: Programming Language :: Python :: 3
Classifier: Programming Language :: Python :: 3.4
Classifier: Programming Language :: Python :: 3.5
Classifier: Programming Language :: Python :: 3.6
